ddbs/__init__.py
ddbs/__main__.py
ddbs-0.0.7.dist-info/LICENSE.txt
ddbs-0.0.7.dist-info/METADATA
ddbs-0.0.7.dist-info/WHEEL
ddbs-0.0.7.dist-info/top_level.txt
ddbs-0.0.7.dist-info/RECORD
