Metadata-Version: 2.1
Name: ddbs
Version: 0.0.7
Summary: A package for injecting a development env into a docker compose project.
Home-page: https://github.com/ZacharyATanenbaum/docker_dev_build_system
Author: Zachary A. Tanenbaum
Author-email: ZachTanenbaum+docker_dev_build_system@gmail.com
License: UNKNOWN
Platform: UNKNOWN
Classifier: Programming Language :: Python :: 3
Classifier: License :: OSI Approved :: MIT License
Classifier: Operating System :: OS Independent
Requires-Python: >=3.6
Requires-Dist: pyyaml
